dv_flow/libhdlsim/__ext__.py
dv_flow/libhdlsim/__init__.py
dv_flow/libhdlsim/flow.dv
dv_flow/libhdlsim/ivl_flow.dv
dv_flow/libhdlsim/ivl_sim_image.py
dv_flow/libhdlsim/ivl_sim_run.py
dv_flow/libhdlsim/mti_flow.dv
dv_flow/libhdlsim/mti_sim_image.py
dv_flow/libhdlsim/mti_sim_run.py
dv_flow/libhdlsim/vcs_flow.dv
dv_flow/libhdlsim/vcs_sim_image.py
dv_flow/libhdlsim/vcs_sim_run.py
dv_flow/libhdlsim/vl_sim_image.py
dv_flow/libhdlsim/vlt_flow.dv
dv_flow/libhdlsim/vlt_sim_image.py
dv_flow/libhdlsim/vlt_sim_run.py
dv_flow/libhdlsim/xcm_flow.dv
dv_flow/libhdlsim/xcm_sim_image.py
dv_flow/libhdlsim/xcm_sim_run.py
dv_flow/libhdlsim/xsm_flow.dv
dv_flow/libhdlsim/xsm_sim_image.py
dv_flow/libhdlsim/xsm_sim_run.py
dv_flow_libhdlim-0.0.1.12981381207a1.dist-info/LICENSE
dv_flow_libhdlim-0.0.1.12981381207a1.dist-info/METADATA
dv_flow_libhdlim-0.0.1.12981381207a1.dist-info/WHEEL
dv_flow_libhdlim-0.0.1.12981381207a1.dist-info/entry_points.txt
dv_flow_libhdlim-0.0.1.12981381207a1.dist-info/top_level.txt
dv_flow_libhdlim-0.0.1.12981381207a1.dist-info/RECORD
