Metadata-Version: 2.2
Name: dv-flow-libhdlim
Version: 0.0.1.12981381207a1
Summary: Provides dv-flow tasks for performing common tasks related to HDL simulation
Author-email: Matthew Ballance <matt.ballance@gmail.com>
License:                                  Apache License
License-File: LICENSE
Requires-Dist: dv-flow-mgr
Requires-Dist: toposort
